odoo/addons/pos_show_clock/README.rst
odoo/addons/pos_show_clock/__init__.py
odoo/addons/pos_show_clock/__manifest__.py
odoo/addons/pos_show_clock/i18n/it.po
odoo/addons/pos_show_clock/i18n/pos_show_clock.pot
odoo/addons/pos_show_clock/readme/CONTRIBUTORS.rst
odoo/addons/pos_show_clock/readme/CREDITS.rst
odoo/addons/pos_show_clock/readme/DESCRIPTION.rst
odoo/addons/pos_show_clock/static/description/icon.png
odoo/addons/pos_show_clock/static/description/index.html
odoo/addons/pos_show_clock/static/description/printscreen.png
odoo/addons/pos_show_clock/static/src/css/pos.css
odoo/addons/pos_show_clock/static/src/js/ChromeWidgets/Clock.js
odoo/addons/pos_show_clock/static/src/xml/ChromeWidgets/Clock.xml
odoo/addons/pos_show_clock/views/pos_template.xml
odoo14_addon_pos_show_clock-14.0.1.0.1.dev10.dist-info/METADATA
odoo14_addon_pos_show_clock-14.0.1.0.1.dev10.dist-info/WHEEL
odoo14_addon_pos_show_clock-14.0.1.0.1.dev10.dist-info/top_level.txt
odoo14_addon_pos_show_clock-14.0.1.0.1.dev10.dist-info/RECORD
