Metadata-Version: 2.1
Name: odoo14-addon-pos-show-clock
Version: 14.0.1.0.1.dev10
Summary: Point of Sale: Display Current Date and Time on POS sreen
Home-page: https://github.com/OCA/pos
Author: KMEE, Odoo Community Association (OCA)
Author-email: support@odoo-community.org
License: LGPL-3
Platform: UNKNOWN
Classifier: Programming Language :: Python
Classifier: Framework :: Odoo
Classifier: Framework :: Odoo :: 14.0
Classifier: License :: OSI Approved :: GNU Lesser General Public License v3 (LGPLv3)
Requires-Python: >=3.6
Requires-Dist: odoo <14.1dev,>=14.0a
